myDataStructure/__init__.py
myDataStructure/my_structure.py
myDataStructure/static_array.py
mydatastructure-0.1.5.dist-info/METADATA
mydatastructure-0.1.5.dist-info/WHEEL
mydatastructure-0.1.5.dist-info/top_level.txt
mydatastructure-0.1.5.dist-info/RECORD
