Metadata-Version: 2.2
Name: myDataStructure
Version: 0.1.5
Summary: A custom data structure package
Home-page: https://github.com/yourusername/myDataStructure
Author: Imanol
Author-email: imanolsupo669@example.com
Classifier: Programming Language :: Python :: 3
Classifier: License :: OSI Approved :: MIT License
Classifier: Operating System :: OS Independent
Requires-Python: >=3.6
Dynamic: author
Dynamic: author-email
Dynamic: classifier
Dynamic: description
Dynamic: description-content-type
Dynamic: home-page
Dynamic: requires-python
Dynamic: summary
